[
  {
    "name": "Glaciate",
    "id": "AV_107",
    "dbfId": 67192,
    "set": "ALTERAC_VALLEY",
    "type": "SPELL"
  },
  {
    "name": "Beaststalker Tavish",
    "id": "AV_113",
    "dbfId": 67803,
    "set": "ALTERAC_VALLEY",
    "type": "HERO"
  },
  {
    "name": "Tamsin's Phylactery",
    "id": "AV_317",
    "dbfId": 67825,
    "set": "ALTERAC_VALLEY",
    "type": "SPELL"
  },
  {
    "name": "Revive Pet",
    "id": "AV_333",
    "dbfId": 70103,
    "set": "ALTERAC_VALLEY",
    "type": "SPELL"
  },
  {
    "name": "Reconnaissance",
    "id": "AV_710",
    "dbfId": 70202,
    "set": "ALTERAC_VALLEY",
    "type": "SPELL"
  },
  {
    "name": "Pack Kodo",
    "id": "BAR_030",
    "dbfId": 62750,
    "set": "THE_BARRENS",
    "type": "MINION"
  },
  {
    "name": "Warsong Wrangler",
    "id": "BAR_037",
    "dbfId": 63088,
    "set": "THE_BARRENS",
    "type": "MINION"
  },
  {
    "name": "Venomous Scorpid",
    "id": "BAR_065",
    "dbfId": 62486,
    "set": "THE_BARRENS",
    "type": "MINION"
  },
  {
    "name": "Southsea Scoundrel",
    "id": "BAR_081",
    "dbfId": 63380,
    "set": "THE_BARRENS",
    "type": "MINION"
  },
  {
    "name": "Yoink!",
    "id": "BAR_323",
    "dbfId": 62894,
    "set": "THE_BARRENS",
    "type": "SPELL"
  },
  {
    "name": "Runed Orb",
    "id": "BAR_541",
    "dbfId": 63056,
    "set": "THE_BARRENS",
    "type": "SPELL"
  },
  {
    "name": "Polymorph: ???",
    "id": "BCON_004",
    "dbfId": 49228,
    "set": "LEGACY",
    "type": "SPELL"
  },
  {
    "name": "Primalfin Lookout",
    "id": "BGS_020",
    "dbfId": 60028,
    "set": "UNGORO",
    "type": "MINION"
  },
  {
    "name": "Tracking",
    "id": "BOM_08_Tracking_004s",
    "dbfId": 84935,
    "set": "ALTERAC_VALLEY",
    "type": "SPELL"
  },
  {
    "name": "Delivery Drone",
    "id": "BOT_238p4",
    "dbfId": 49367,
    "set": "BOOMSDAY",
    "type": "HERO_POWER"
  },
  {
    "name": "Myra Rotspring",
    "id": "BOT_243",
    "dbfId": 48159,
    "set": "BOOMSDAY",
    "type": "MINION"
  },
  {
    "name": "Omega Assembly",
    "id": "BOT_299",
    "dbfId": 48515,
    "set": "BOOMSDAY",
    "type": "SPELL"
  },
  {
    "name": "Secret Plan",
    "id": "BOT_402",
    "dbfId": 48519,
    "set": "BOOMSDAY",
    "type": "SPELL"
  },
  {
    "name": "Dendrologist",
    "id": "BOT_419",
    "dbfId": 49621,
    "set": "BOOMSDAY",
    "type": "MINION"
  },
  {
    "name": "Cloning Device",
    "id": "BOT_435",
    "dbfId": 48759,
    "set": "BOOMSDAY",
    "type": "SPELL"
  },
  {
    "name": "Arcane Dynamo",
    "id": "BOT_539",
    "dbfId": 49171,
    "set": "BOOMSDAY",
    "type": "MINION"
  },
  {
    "name": "Font of Power",
    "id": "BT_021",
    "dbfId": 56460,
    "set": "BLACK_TEMPLE",
    "type": "SPELL"
  },
  {
    "name": "Marshspawn",
    "id": "BT_115",
    "dbfId": 56472,
    "set": "BLACK_TEMPLE",
    "type": "MINION"
  },
  {
    "name": "Renew",
    "id": "BT_252",
    "dbfId": 56595,
    "set": "BLACK_TEMPLE",
    "type": "SPELL"
  },
  {
    "name": "Netherwalker",
    "id": "BT_321",
    "dbfId": 56985,
    "set": "BLACK_TEMPLE",
    "type": "MINION"
  },
  {
    "name": "The Right Tool",
    "id": "BTA_01p",
    "dbfId": 62009,
    "set": "BLACK_TEMPLE",
    "type": "HERO_POWER"
  },
  {
    "name": "Finders Keepers",
    "id": "CFM_313",
    "dbfId": 40423,
    "set": "GANGS",
    "type": "SPELL"
  },
  {
    "name": "Grimestreet Informant",
    "id": "CFM_321",
    "dbfId": 40474,
    "set": "GANGS",
    "type": "MINION"
  },
  {
    "name": "Drakonid Operative",
    "id": "CFM_605",
    "dbfId": 40378,
    "set": "GANGS",
    "type": "MINION"
  },
  {
    "name": "Kabal Courier",
    "id": "CFM_649",
    "dbfId": 40496,
    "set": "GANGS",
    "type": "MINION"
  },
  {
    "name": "Lotus Agents",
    "id": "CFM_852",
    "dbfId": 40742,
    "set": "GANGS",
    "type": "MINION"
  },
  {
    "name": "I Know a Guy",
    "id": "CFM_940",
    "dbfId": 40839,
    "set": "GANGS",
    "type": "SPELL"
  },
  {
    "name": "Drakonid Operative",
    "id": "CORE_CFM_605",
    "dbfId": 86535,
    "set": "CORE",
    "type": "MINION"
  },
  {
    "name": "Marked Shot",
    "id": "CORE_DAL_371",
    "dbfId": 76300,
    "set": "CORE",
    "type": "SPELL"
  },
  {
    "name": "Hench-Clan Burglar",
    "id": "CORE_DAL_416",
    "dbfId": 86540,
    "set": "CORE",
    "type": "MINION"
  },
  {
    "name": "Kalecgos",
    "id": "CORE_DAL_609",
    "dbfId": 76271,
    "set": "PLACEHOLDER_202204",
    "type": "MINION"
  },
  {
    "name": "Bronze Explorer",
    "id": "CORE_DRG_229",
    "dbfId": 86545,
    "set": "CORE",
    "type": "MINION"
  },
  {
    "name": "Tracking",
    "id": "CORE_DS1_184",
    "dbfId": 69545,
    "set": "CORE",
    "type": "SPELL"
  },
  {
    "name": "Ethereal Conjurer",
    "id": "CORE_LOE_003",
    "dbfId": 69701,
    "set": "PLACEHOLDER_202204",
    "type": "MINION"
  },
  {
    "name": "Gorillabot A-3",
    "id": "CORE_LOE_039",
    "dbfId": 86548,
    "set": "CORE",
    "type": "MINION"
  },
  {
    "name": "Sir Finley Mrrgglton",
    "id": "CORE_LOE_076",
    "dbfId": 76311,
    "set": "PLACEHOLDER_202204",
    "type": "MINION"
  },
  {
    "name": "Frightened Flunky",
    "id": "CORE_ULD_195",
    "dbfId": 102719,
    "set": "CORE",
    "type": "MINION"
  },
  {
    "name": "Vulpera Scoundrel",
    "id": "CORE_ULD_209",
    "dbfId": 86551,
    "set": "CORE",
    "type": "MINION"
  },
  {
    "name": "Illidari Studies",
    "id": "CORE_YOP_001",
    "dbfId": 97377,
    "set": "CORE",
    "type": "SPELL"
  },
  {
    "name": "Selective Breeder",
    "id": "CS3_015",
    "dbfId": 62698,
    "set": "CORE",
    "type": "MINION"
  },
  {
    "name": "Thrive in the Shadows",
    "id": "CS3_028",
    "dbfId": 66861,
    "set": "CORE",
    "type": "SPELL"
  },
  {
    "name": "Messenger Raven",
    "id": "DAL_163",
    "dbfId": 51943,
    "set": "DALARAN",
    "type": "MINION"
  },
  {
    "name": "Crystalsong Portal",
    "id": "DAL_352",
    "dbfId": 51781,
    "set": "DALARAN",
    "type": "SPELL"
  },
  {
    "name": "Marked Shot",
    "id": "DAL_371",
    "dbfId": 52070,
    "set": "DALARAN",
    "type": "SPELL"
  },
  {
    "name": "Nine Lives",
    "id": "DAL_377",
    "dbfId": 52082,
    "set": "DALARAN",
    "type": "SPELL"
  },
  {
    "name": "Hench-Clan Burglar",
    "id": "DAL_416",
    "dbfId": 52112,
    "set": "DALARAN",
    "type": "MINION"
  },
  {
    "name": "Power of Creation",
    "id": "DAL_578",
    "dbfId": 52640,
    "set": "DALARAN",
    "type": "SPELL"
  },
  {
    "name": "Cobalt Leyline",
    "id": "DAL_579p",
    "dbfId": 52643,
    "set": "DALARAN",
    "type": "HERO_POWER"
  },
  {
    "name": "Magic Trick",
    "id": "DAL_608",
    "dbfId": 52991,
    "set": "DALARAN",
    "type": "SPELL"
  },
  {
    "name": "Kalecgos",
    "id": "DAL_609",
    "dbfId": 53002,
    "set": "DALARAN",
    "type": "MINION"
  },
  {
    "name": "Madame Lazul",
    "id": "DAL_729",
    "dbfId": 52715,
    "set": "DALARAN",
    "type": "MINION"
  },
  {
    "name": "Archivist Elysiana",
    "id": "DAL_736",
    "dbfId": 52870,
    "set": "DALARAN",
    "type": "MINION"
  },
  {
    "name": "Ethereal Lackey",
    "id": "DAL_741",
    "dbfId": 52900,
    "set": "DALARAN",
    "type": "MINION"
  },
  {
    "name": "Dreamgrove Ring",
    "id": "DALA_711",
    "dbfId": 54001,
    "set": "DALARAN",
    "type": "SPELL"
  },
  {
    "name": "Case Study",
    "id": "DALA_717",
    "dbfId": 54005,
    "set": "DALARAN",
    "type": "SPELL"
  },
  {
    "name": "Recruit a Veteran",
    "id": "DALA_907",
    "dbfId": 54614,
    "set": "DALARAN",
    "type": "SPELL"
  },
  {
    "name": "Moonlit Guidance",
    "id": "DED_002",
    "dbfId": 65583,
    "set": "STORMWIND",
    "type": "SPELL"
  },
  {
    "name": "Ring Toss",
    "id": "DMF_105",
    "dbfId": 61291,
    "set": "DARKMOON_FAIRE",
    "type": "SPELL"
  },
  {
    "name": "Ring Toss",
    "id": "DMF_105t",
    "dbfId": 61292,
    "set": "DARKMOON_FAIRE",
    "type": "SPELL"
  },
  {
    "name": "Mystery Winner",
    "id": "DMF_122",
    "dbfId": 61682,
    "set": "DARKMOON_FAIRE",
    "type": "MINION"
  },
  {
    "name": "Palm Reading",
    "id": "DMF_187",
    "dbfId": 61282,
    "set": "DARKMOON_FAIRE",
    "type": "SPELL"
  },
  {
    "name": "Dragon's Hoard",
    "id": "DRG_028",
    "dbfId": 55095,
    "set": "DRAGONS",
    "type": "SPELL"
  },
  {
    "name": "Draconic Lackey",
    "id": "DRG_052",
    "dbfId": 55378,
    "set": "DRAGONS",
    "type": "MINION"
  },
  {
    "name": "Chromatic Egg",
    "id": "DRG_086",
    "dbfId": 55454,
    "set": "DRAGONS",
    "type": "MINION"
  },
  {
    "name": "Azure Explorer",
    "id": "DRG_102",
    "dbfId": 54901,
    "set": "DRAGONS",
    "type": "MINION"
  },
  {
    "name": "Arcane Breath",
    "id": "DRG_106",
    "dbfId": 54906,
    "set": "DRAGONS",
    "type": "SPELL"
  },
  {
    "name": "Bronze Explorer",
    "id": "DRG_229",
    "dbfId": 55056,
    "set": "DRAGONS",
    "type": "MINION"
  },
  {
    "name": "Primordial Explorer",
    "id": "DRG_254",
    "dbfId": 55294,
    "set": "DRAGONS",
    "type": "MINION"
  },
  {
    "name": "Malygos, Aspect of Magic",
    "id": "DRG_270",
    "dbfId": 56161,
    "set": "DRAGONS",
    "type": "MINION"
  },
  {
    "name": "Emerald Explorer",
    "id": "DRG_313",
    "dbfId": 55037,
    "set": "DRAGONS",
    "type": "MINION"
  },
  {
    "name": "Fortune",
    "id": "DRGA_BOSS_09p",
    "dbfId": 58278,
    "set": "YEAR_OF_THE_DRAGON",
    "type": "HERO_POWER"
  },
  {
    "name": "Fortune",
    "id": "DRGA_BOSS_09p_H",
    "dbfId": 61327,
    "set": "YEAR_OF_THE_DRAGON",
    "type": "HERO_POWER"
  },
  {
    "name": "Tracking",
    "id": "DS1_184",
    "dbfId": 1047,
    "set": "LEGACY",
    "type": "SPELL"
  },
  {
    "name": "Harmonica Soloist",
    "id": "ETC_028",
    "dbfId": 87642,
    "set": "BATTLE_OF_THE_BANDS",
    "type": "MINION"
  },
  {
    "name": "Mixtape",
    "id": "ETC_074",
    "dbfId": 90583,
    "set": "BATTLE_OF_THE_BANDS",
    "type": "SPELL"
  },
  {
    "name": "E.T.C., Band Manager",
    "id": "ETC_080",
    "dbfId": 90749,
    "set": "BATTLE_OF_THE_BANDS",
    "type": "MINION"
  },
  {
    "name": "Demonic Dynamics",
    "id": "ETC_083",
    "dbfId": 90994,
    "set": "BATTLE_OF_THE_BANDS",
    "type": "SPELL"
  },
  {
    "name": "Symphony of Sins",
    "id": "ETC_085",
    "dbfId": 91001,
    "set": "BATTLE_OF_THE_BANDS",
    "type": "SPELL"
  },
  {
    "name": "Ghost Writer",
    "id": "ETC_088",
    "dbfId": 91080,
    "set": "BATTLE_OF_THE_BANDS",
    "type": "MINION"
  },
  {
    "name": "Hipster",
    "id": "ETC_103",
    "dbfId": 91989,
    "set": "BATTLE_OF_THE_BANDS",
    "type": "MINION"
  },
  {
    "name": "Volume Up",
    "id": "ETC_205",
    "dbfId": 97360,
    "set": "BATTLE_OF_THE_BANDS",
    "type": "SPELL"
  },
  {
    "name": "Infinitize the Maxitude",
    "id": "ETC_206",
    "dbfId": 97361,
    "set": "BATTLE_OF_THE_BANDS",
    "type": "SPELL"
  },
  {
    "name": "Paparazzi",
    "id": "ETC_326",
    "dbfId": 90700,
    "set": "BATTLE_OF_THE_BANDS",
    "type": "MINION"
  },
  {
    "name": "Flowrider",
    "id": "ETC_359",
    "dbfId": 92228,
    "set": "BATTLE_OF_THE_BANDS",
    "type": "MINION"
  },
  {
    "name": "Happy Hippie",
    "id": "ETC_375b",
    "dbfId": 97388,
    "set": "BATTLE_OF_THE_BANDS",
    "type": "SPELL"
  },
  {
    "name": "Taste of Chaos",
    "id": "ETC_394",
    "dbfId": 96946,
    "set": "BATTLE_OF_THE_BANDS",
    "type": "SPELL"
  },
  {
    "name": "Harmonic Disco",
    "id": "ETC_506",
    "dbfId": 88580,
    "set": "BATTLE_OF_THE_BANDS",
    "type": "SPELL"
  },
  {
    "name": "Dissonant Disco",
    "id": "ETC_506t",
    "dbfId": 88555,
    "set": "BATTLE_OF_THE_BANDS",
    "type": "SPELL"
  },
  {
    "name": "Rewind",
    "id": "ETC_532",
    "dbfId": 90592,
    "set": "BATTLE_OF_THE_BANDS",
    "type": "SPELL"
  },
  {
    "name": "Archivist Elysiana",
    "id": "FB_Champs_DAL_736",
    "dbfId": 61008,
    "set": "TB",
    "type": "MINION"
  },
  {
    "name": "Join Forces",
    "id": "FB_Toki2_Hero",
    "dbfId": 50155,
    "set": "TB",
    "type": "HERO_POWER"
  },
  {
    "name": "Arcane Keysmith",
    "id": "GIL_116",
    "dbfId": 46654,
    "set": "GILNEAS",
    "type": "MINION"
  },
  {
    "name": "Dark Possession",
    "id": "GIL_543",
    "dbfId": 47033,
    "set": "GILNEAS",
    "type": "SPELL"
  },
  {
    "name": "Blazing Invocation",
    "id": "GIL_836",
    "dbfId": 48393,
    "set": "GILNEAS",
    "type": "SPELL"
  },
  {
    "name": "Scavenge",
    "id": "GILA_500p2",
    "dbfId": 48590,
    "set": "GILNEAS",
    "type": "HERO_POWER"
  },
  {
    "name": "Tools of the Trade",
    "id": "GILA_510",
    "dbfId": 49155,
    "set": "GILNEAS",
    "type": "SPELL"
  },
  {
    "name": "Cartographer",
    "id": "GILA_802",
    "dbfId": 48352,
    "set": "GILNEAS",
    "type": "MINION"
  },
  {
    "name": "Brass Lantern",
    "id": "GILA_806",
    "dbfId": 48359,
    "set": "GILNEAS",
    "type": "SPELL"
  },
  {
    "name": "Eternal Servitude",
    "id": "ICC_213",
    "dbfId": 42597,
    "set": "ICECROWN",
    "type": "SPELL"
  },
  {
    "name": "Stitched Tracker",
    "id": "ICC_415",
    "dbfId": 42707,
    "set": "ICECROWN",
    "type": "MINION"
  },
  {
    "name": "Ivory Knight",
    "id": "KAR_057",
    "dbfId": 39439,
    "set": "KARA",
    "type": "MINION"
  },
  {
    "name": "Netherspite Historian",
    "id": "KAR_062",
    "dbfId": 39554,
    "set": "KARA",
    "type": "MINION"
  },
  {
    "name": "Castle",
    "id": "KAR_A10_22",
    "dbfId": 39544,
    "set": "KARA",
    "type": "HERO_POWER"
  },
  {
    "name": "Ethereal Conjurer",
    "id": "LOE_003",
    "dbfId": 2875,
    "set": "LOE",
    "type": "MINION"
  },
  {
    "name": "Museum Curator",
    "id": "LOE_006",
    "dbfId": 2878,
    "set": "LOE",
    "type": "MINION"
  },
  {
    "name": "Dark Peddler",
    "id": "LOE_023",
    "dbfId": 2895,
    "set": "LOE",
    "type": "MINION"
  },
  {
    "name": "Jeweled Scarab",
    "id": "LOE_029",
    "dbfId": 2901,
    "set": "LOE",
    "type": "MINION"
  },
  {
    "name": "Gorillabot A-3",
    "id": "LOE_039",
    "dbfId": 2911,
    "set": "LOE",
    "type": "MINION"
  },
  {
    "name": "Tomb Spider",
    "id": "LOE_047",
    "dbfId": 2919,
    "set": "LOE",
    "type": "MINION"
  },
  {
    "name": "Sir Finley Mrrgglton",
    "id": "LOE_076",
    "dbfId": 2948,
    "set": "LOE",
    "type": "MINION"
  },
  {
    "name": "Arch-Thief Rafaam",
    "id": "LOE_092",
    "dbfId": 2964,
    "set": "LOE",
    "type": "MINION"
  },
  {
    "name": "Raven Idol",
    "id": "LOE_115",
    "dbfId": 13335,
    "set": "LOE",
    "type": "SPELL"
  },
  {
    "name": "Break Free",
    "id": "LOE_115a",
    "dbfId": 38112,
    "set": "LOE",
    "type": "SPELL"
  },
  {
    "name": "Awakened",
    "id": "LOE_115b",
    "dbfId": 38113,
    "set": "LOE",
    "type": "SPELL"
  },
  {
    "name": "Wish for Power",
    "id": "LOEA02_03",
    "dbfId": 14282,
    "set": "LOE",
    "type": "SPELL"
  },
  {
    "name": "Wish for Valor",
    "id": "LOEA02_04",
    "dbfId": 14283,
    "set": "LOE",
    "type": "SPELL"
  },
  {
    "name": "Wish for Glory",
    "id": "LOEA02_05",
    "dbfId": 14284,
    "set": "LOE",
    "type": "SPELL"
  },
  {
    "name": "Wish for Companionship",
    "id": "LOEA02_10",
    "dbfId": 25073,
    "set": "LOE",
    "type": "SPELL"
  },
  {
    "name": "Eye of Orsis",
    "id": "LOEA16_13",
    "dbfId": 25393,
    "set": "LOE",
    "type": "SPELL"
  },
  {
    "name": "The Runespear",
    "id": "LOOT_506",
    "dbfId": 46305,
    "set": "LOOTAPALOOZA",
    "type": "WEAPON"
  },
  {
    "name": "Zarog's Crown",
    "id": "LOOT_998j",
    "dbfId": 43180,
    "set": "LOOTAPALOOZA",
    "type": "SPELL"
  },
  {
    "name": "Portable Forge",
    "id": "LOOTA_841",
    "dbfId": 47042,
    "set": "LOOTAPALOOZA",
    "type": "SPELL"
  },
  {
    "name": "Felosophical Insight {0}",
    "id": "LT23_024T1_01",
    "dbfId": 94843,
    "set": "LETTUCE",
    "type": "LETTUCE_ABILITY"
  },
  {
    "name": "Dragonflight Respite {0}",
    "id": "LT24_002T1_01",
    "dbfId": 94752,
    "set": "LETTUCE",
    "type": "LETTUCE_ABILITY"
  },
  {
    "name": "Murlocology 1",
    "id": "LT24_003P2_01",
    "dbfId": 94234,
    "set": "LETTUCE",
    "type": "LETTUCE_ABILITY"
  },
  {
    "name": "Murlocology 2",
    "id": "LT24_003P2_02",
    "dbfId": 94233,
    "set": "LETTUCE",
    "type": "LETTUCE_ABILITY"
  },
  {
    "name": "Murlocology 3",
    "id": "LT24_003P2_03",
    "dbfId": 94232,
    "set": "LETTUCE",
    "type": "LETTUCE_ABILITY"
  },
  {
    "name": "Murlocology 4",
    "id": "LT24_003P2_04",
    "dbfId": 94231,
    "set": "LETTUCE",
    "type": "LETTUCE_ABILITY"
  },
  {
    "name": "Murlocology {0}",
    "id": "LT24_003P2_05",
    "dbfId": 93963,
    "set": "LETTUCE",
    "type": "LETTUCE_ABILITY"
  },
  {
    "name": "One And The Same 1",
    "id": "LT24_006P3_01",
    "dbfId": 95924,
    "set": "LETTUCE",
    "type": "LETTUCE_ABILITY"
  },
  {
    "name": "One And The Same 2",
    "id": "LT24_006P3_02",
    "dbfId": 95923,
    "set": "LETTUCE",
    "type": "LETTUCE_ABILITY"
  },
  {
    "name": "One And The Same 3",
    "id": "LT24_006P3_03",
    "dbfId": 95922,
    "set": "LETTUCE",
    "type": "LETTUCE_ABILITY"
  },
  {
    "name": "One And The Same 4",
    "id": "LT24_006P3_04",
    "dbfId": 95921,
    "set": "LETTUCE",
    "type": "LETTUCE_ABILITY"
  },
  {
    "name": "One And The Same {0}",
    "id": "LT24_006P3_05",
    "dbfId": 94922,
    "set": "LETTUCE",
    "type": "LETTUCE_ABILITY"
  },
  {
    "name": "Princess Power! 1",
    "id": "LT24_011P3_01",
    "dbfId": 95881,
    "set": "LETTUCE",
    "type": "LETTUCE_ABILITY"
  },
  {
    "name": "Princess Power! 2",
    "id": "LT24_011P3_02",
    "dbfId": 95880,
    "set": "LETTUCE",
    "type": "LETTUCE_ABILITY"
  },
  {
    "name": "Princess Power! 3",
    "id": "LT24_011P3_03",
    "dbfId": 95879,
    "set": "LETTUCE",
    "type": "LETTUCE_ABILITY"
  },
  {
    "name": "Princess Power! 4",
    "id": "LT24_011P3_04",
    "dbfId": 95878,
    "set": "LETTUCE",
    "type": "LETTUCE_ABILITY"
  },
  {
    "name": "Princess Power! {0}",
    "id": "LT24_011P3_05",
    "dbfId": 93388,
    "set": "LETTUCE",
    "type": "LETTUCE_ABILITY"
  },
  {
    "name": "Triune Supremacy 1",
    "id": "LT24_020P6_01",
    "dbfId": 94339,
    "set": "LETTUCE",
    "type": "LETTUCE_ABILITY"
  },
  {
    "name": "Triune Supremacy 2",
    "id": "LT24_020P6_02",
    "dbfId": 94338,
    "set": "LETTUCE",
    "type": "LETTUCE_ABILITY"
  },
  {
    "name": "Triune Supremacy 3",
    "id": "LT24_020P6_03",
    "dbfId": 94337,
    "set": "LETTUCE",
    "type": "LETTUCE_ABILITY"
  },
  {
    "name": "Triune Supremacy 4",
    "id": "LT24_020P6_04",
    "dbfId": 94336,
    "set": "LETTUCE",
    "type": "LETTUCE_ABILITY"
  },
  {
    "name": "Triune Supremacy {0}",
    "id": "LT24_020P6_05",
    "dbfId": 93459,
    "set": "LETTUCE",
    "type": "LETTUCE_ABILITY"
  },
  {
    "name": "Habeas Corpses",
    "id": "MAW_002",
    "dbfId": 79540,
    "set": "REVENDRETH",
    "type": "SPELL"
  },
  {
    "name": "Defense Attorney Nathanos",
    "id": "MAW_011",
    "dbfId": 79556,
    "set": "REVENDRETH",
    "type": "MINION"
  },
  {
    "name": "Perjury",
    "id": "MAW_018",
    "dbfId": 79607,
    "set": "REVENDRETH",
    "type": "SPELL"
  },
  {
    "name": "Whirlweaver",
    "id": "NX2_003",
    "dbfId": 86440,
    "set": "RETURN_OF_THE_LICH_KING",
    "type": "MINION"
  },
  {
    "name": "Blazing Transmutation",
    "id": "NX2_008",
    "dbfId": 86504,
    "set": "RETURN_OF_THE_LICH_KING",
    "type": "SPELL"
  },
  {
    "name": "Faithful Companions",
    "id": "NX2_015",
    "dbfId": 86574,
    "set": "RETURN_OF_THE_LICH_KING",
    "type": "SPELL"
  },
  {
    "name": "Training Session",
    "id": "NX2_029",
    "dbfId": 86693,
    "set": "RETURN_OF_THE_LICH_KING",
    "type": "SPELL"
  },
  {
    "name": "Suspicious Peddler",
    "id": "NX2_044",
    "dbfId": 87285,
    "set": "RETURN_OF_THE_LICH_KING",
    "type": "MINION"
  },
  {
    "name": "Journey Below",
    "id": "OG_072",
    "dbfId": 38393,
    "set": "OG",
    "type": "SPELL"
  },
  {
    "name": "A Light in the Darkness",
    "id": "OG_311",
    "dbfId": 38913,
    "set": "OG",
    "type": "SPELL"
  },
  {
    "name": "Raid Negotiator",
    "id": "ONY_019",
    "dbfId": 71242,
    "set": "ALTERAC_VALLEY",
    "type": "MINION"
  },
  {
    "name": "Battle Vicar",
    "id": "ONY_022",
    "dbfId": 71248,
    "set": "ALTERAC_VALLEY",
    "type": "MINION"
  },
  {
    "name": "Drakefire Amulet",
    "id": "ONY_029",
    "dbfId": 71290,
    "set": "ALTERAC_VALLEY",
    "type": "SPELL"
  },
  {
    "name": "Tooth of Nefarian",
    "id": "ONY_032",
    "dbfId": 71289,
    "set": "ALTERAC_VALLEY",
    "type": "SPELL"
  },
  {
    "name": "Suspicious Alchemist",
    "id": "REV_000",
    "dbfId": 75866,
    "set": "REVENDRETH",
    "type": "MINION"
  },
  {
    "name": "Suspicious Usher",
    "id": "REV_002",
    "dbfId": 75922,
    "set": "REVENDRETH",
    "type": "MINION"
  },
  {
    "name": "Suspicious Pirate",
    "id": "REV_006",
    "dbfId": 75910,
    "set": "REVENDRETH",
    "type": "MINION"
  },
  {
    "name": "Theotar, the Mad Duke",
    "id": "REV_238",
    "dbfId": 76984,
    "set": "REVENDRETH",
    "type": "MINION"
  },
  {
    "name": "Identity Theft",
    "id": "REV_253",
    "dbfId": 77368,
    "set": "REVENDRETH",
    "type": "SPELL"
  },
  {
    "name": "Nightshade Bud",
    "id": "REV_311",
    "dbfId": 77562,
    "set": "REVENDRETH",
    "type": "SPELL"
  },
  {
    "name": "Sunlight Blossom",
    "id": "REV_311t",
    "dbfId": 84430,
    "set": "REVENDRETH",
    "type": "SPELL"
  },
  {
    "name": "Moonlight Blossom",
    "id": "REV_311t2",
    "dbfId": 84432,
    "set": "REVENDRETH",
    "type": "SPELL"
  },
  {
    "name": "Planted Evidence",
    "id": "REV_313",
    "dbfId": 77654,
    "set": "REVENDRETH",
    "type": "SPELL"
  },
  {
    "name": "Dispossessed Soul",
    "id": "REV_901",
    "dbfId": 75876,
    "set": "REVENDRETH",
    "type": "MINION"
  },
  {
    "name": "Artificer Xy'mox",
    "id": "REV_937",
    "dbfId": 77482,
    "set": "REVENDRETH",
    "type": "MINION"
  },
  {
    "name": "Sketchy Stranger",
    "id": "REV_945",
    "dbfId": 77714,
    "set": "REVENDRETH",
    "type": "MINION"
  },
  {
    "name": "Muckborn Servant",
    "id": "REV_947",
    "dbfId": 78080,
    "set": "REVENDRETH",
    "type": "MINION"
  },
  {
    "name": "Service Bell",
    "id": "REV_948",
    "dbfId": 78081,
    "set": "REVENDRETH",
    "type": "SPELL"
  },
  {
    "name": "Legendary Invitation",
    "id": "REV_951t",
    "dbfId": 79922,
    "set": "REVENDRETH",
    "type": "SPELL"
  },
  {
    "name": "Bound Soul",
    "id": "RLK_214t",
    "dbfId": 84246,
    "set": "RETURN_OF_THE_LICH_KING",
    "type": "SPELL"
  },
  {
    "name": "Prismatic Elemental",
    "id": "RLK_547",
    "dbfId": 85034,
    "set": "RETURN_OF_THE_LICH_KING",
    "type": "MINION"
  },
  {
    "name": "Potion Belt",
    "id": "RLK_569",
    "dbfId": 86111,
    "set": "RETURN_OF_THE_LICH_KING",
    "type": "SPELL"
  },
  {
    "name": "Vision of Darkness",
    "id": "RLK_816t3",
    "dbfId": 85059,
    "set": "RETURN_OF_THE_LICH_KING",
    "type": "SPELL"
  },
  {
    "name": "Arcane Quiver",
    "id": "RLK_817",
    "dbfId": 84237,
    "set": "RETURN_OF_THE_LICH_KING",
    "type": "SPELL"
  },
  {
    "name": "Nerubian Vizier",
    "id": "RLK_834",
    "dbfId": 85154,
    "set": "RETURN_OF_THE_LICH_KING",
    "type": "MINION"
  },
  {
    "name": "Flight of the Bronze",
    "id": "RLK_917",
    "dbfId": 84391,
    "set": "RETURN_OF_THE_LICH_KING",
    "type": "SPELL"
  },
  {
    "name": "Arcane Quiver",
    "id": "RLK_Prologue_RLK_817",
    "dbfId": 100778,
    "set": "RETURN_OF_THE_LICH_KING",
    "type": "SPELL"
  },
  {
    "name": "Illidari Studies",
    "id": "RLK_Prologue_YOP_001",
    "dbfId": 100814,
    "set": "DARKMOON_FAIRE",
    "type": "SPELL"
  },
  {
    "name": "Demonic Studies",
    "id": "SCH_158",
    "dbfId": 59628,
    "set": "SCHOLOMANCE",
    "type": "SPELL"
  },
  {
    "name": "Transfer Student",
    "id": "SCH_199t21",
    "dbfId": 60590,
    "set": "SCHOLOMANCE",
    "type": "MINION"
  },
  {
    "name": "Transfer Student",
    "id": "SCH_199t30",
    "dbfId": 87358,
    "set": "SCHOLOMANCE",
    "type": "MINION"
  },
  {
    "name": "Transfer Student",
    "id": "SCH_199t31",
    "dbfId": 95005,
    "set": "SCHOLOMANCE",
    "type": "MINION"
  },
  {
    "name": "Transfer Student",
    "id": "SCH_199t32",
    "dbfId": 97812,
    "set": "SCHOLOMANCE",
    "type": "MINION"
  },
  {
    "name": "Transfer Student",
    "id": "SCH_199t33",
    "dbfId": 102269,
    "set": "SCHOLOMANCE",
    "type": "MINION"
  },
  {
    "name": "Transfer Student",
    "id": "SCH_199t9",
    "dbfId": 60575,
    "set": "SCHOLOMANCE",
    "type": "MINION"
  },
  {
    "name": "Draconic Studies",
    "id": "SCH_233",
    "dbfId": 58974,
    "set": "SCHOLOMANCE",
    "type": "SPELL"
  },
  {
    "name": "Athletic Studies",
    "id": "SCH_237",
    "dbfId": 58978,
    "set": "SCHOLOMANCE",
    "type": "SPELL"
  },
  {
    "name": "Steward of Scrolls",
    "id": "SCH_245",
    "dbfId": 59027,
    "set": "SCHOLOMANCE",
    "type": "MINION"
  },
  {
    "name": "Primordial Studies",
    "id": "SCH_270",
    "dbfId": 59213,
    "set": "SCHOLOMANCE",
    "type": "SPELL"
  },
  {
    "name": "Carrion Studies",
    "id": "SCH_300",
    "dbfId": 58782,
    "set": "SCHOLOMANCE",
    "type": "SPELL"
  },
  {
    "name": "Nature Studies",
    "id": "SCH_333",
    "dbfId": 59163,
    "set": "SCHOLOMANCE",
    "type": "SPELL"
  },
  {
    "name": "Wand Thief",
    "id": "SCH_350",
    "dbfId": 59556,
    "set": "SCHOLOMANCE",
    "type": "MINION"
  },
  {
    "name": "Instructor Fireheart",
    "id": "SCH_507",
    "dbfId": 59164,
    "set": "SCHOLOMANCE",
    "type": "MINION"
  },
  {
    "name": "Charged Call",
    "id": "SW_035",
    "dbfId": 64356,
    "set": "STORMWIND",
    "type": "SPELL"
  },
  {
    "name": "Blessed Goods",
    "id": "SW_049",
    "dbfId": 64661,
    "set": "STORMWIND",
    "type": "SPELL"
  },
  {
    "name": "Deeprun Engineer",
    "id": "SW_059",
    "dbfId": 64707,
    "set": "STORMWIND",
    "type": "MINION"
  },
  {
    "name": "Pandaren Importer",
    "id": "SW_065",
    "dbfId": 64713,
    "set": "STORMWIND",
    "type": "MINION"
  },
  {
    "name": "Entrapped Sorceress",
    "id": "SW_400",
    "dbfId": 63821,
    "set": "STORMWIND",
    "type": "MINION"
  },
  {
    "name": "Discover the Void Shard",
    "id": "SW_433t",
    "dbfId": 64350,
    "set": "STORMWIND",
    "type": "SPELL"
  },
  {
    "name": "Call of the Grave",
    "id": "SW_440",
    "dbfId": 64390,
    "set": "STORMWIND",
    "type": "SPELL"
  },
  {
    "name": "Primalfin Lookout",
    "id": "TB_BaconUps_089",
    "dbfId": 60027,
    "set": "UNGORO",
    "type": "MINION"
  },
  {
    "name": "Castle",
    "id": "TB_BBR3_BOSS_09p",
    "dbfId": 64826,
    "set": "TB",
    "type": "HERO_POWER"
  },
  {
    "name": "PH Voone Charge",
    "id": "TB_BotB_Voone_001p",
    "dbfId": 98675,
    "set": "TB",
    "type": "HERO_POWER"
  },
  {
    "name": "Castle",
    "id": "TB_CheaterChess_Black",
    "dbfId": 51180,
    "set": "TB",
    "type": "HERO_POWER"
  },
  {
    "name": "Master Schemer",
    "id": "TB_EVILBRM_RafaamHeroPower2",
    "dbfId": 59617,
    "set": "TB",
    "type": "HERO_POWER"
  },
  {
    "name": "Magic of Azeroth",
    "id": "TB_MagicalGuardians_MagicSpell",
    "dbfId": 96963,
    "set": "TB",
    "type": "SPELL"
  },
  {
    "name": "Dark Flight Malygos",
    "id": "TB_MagicalGuardians_Malygos",
    "dbfId": 96978,
    "set": "TB",
    "type": "MINION"
  },
  {
    "name": "Déjà Vu",
    "id": "TOT_108",
    "dbfId": 51049,
    "set": "TAVERNS_OF_TIME",
    "type": "SPELL"
  },
  {
    "name": "Draconic Herald",
    "id": "TOT_316",
    "dbfId": 51072,
    "set": "TAVERNS_OF_TIME",
    "type": "MINION"
  },
  {
    "name": "Ripple in Time",
    "id": "TOT_345",
    "dbfId": 51151,
    "set": "TAVERNS_OF_TIME",
    "type": "SPELL"
  },
  {
    "name": "Haunting Visions",
    "id": "TRL_058",
    "dbfId": 49802,
    "set": "TROLL",
    "type": "SPELL"
  },
  {
    "name": "Gurubashi Hypemon",
    "id": "TRL_077",
    "dbfId": 49847,
    "set": "TROLL",
    "type": "MINION"
  },
  {
    "name": "Griftah",
    "id": "TRL_096",
    "dbfId": 50009,
    "set": "TROLL",
    "type": "MINION"
  },
  {
    "name": "Stolen Steel",
    "id": "TRL_156",
    "dbfId": 50749,
    "set": "TROLL",
    "type": "SPELL"
  },
  {
    "name": "A New Challenger...",
    "id": "TRL_305",
    "dbfId": 50019,
    "set": "TROLL",
    "type": "SPELL"
  },
  {
    "name": "Master's Call",
    "id": "TRL_339",
    "dbfId": 50212,
    "set": "TROLL",
    "type": "SPELL"
  },
  {
    "name": "Bloodscalp Strategist",
    "id": "TRL_349",
    "dbfId": 50471,
    "set": "TROLL",
    "type": "MINION"
  },
  {
    "name": "Firetree Witchdoctor",
    "id": "TRL_523",
    "dbfId": 50408,
    "set": "TROLL",
    "type": "MINION"
  },
  {
    "name": "Croak Jouster",
    "id": "TRLA_159",
    "dbfId": 52885,
    "set": "TROLL",
    "type": "MINION"
  },
  {
    "name": "Redcrest Rocker",
    "id": "TRLA_173",
    "dbfId": 52910,
    "set": "TROLL",
    "type": "MINION"
  },
  {
    "name": "School Teacher",
    "id": "TSC_052",
    "dbfId": 72598,
    "set": "THE_SUNKEN_CITY",
    "type": "MINION"
  },
  {
    "name": "Amalgam of the Deep",
    "id": "TSC_069",
    "dbfId": 73906,
    "set": "THE_SUNKEN_CITY",
    "type": "MINION"
  },
  {
    "name": "Spellcoiler",
    "id": "TSC_643",
    "dbfId": 72924,
    "set": "THE_SUNKEN_CITY",
    "type": "MINION"
  },
  {
    "name": "Nellie, the Great Thresher",
    "id": "TSC_660",
    "dbfId": 74894,
    "set": "THE_SUNKEN_CITY",
    "type": "MINION"
  },
  {
    "name": "Azsharan Scroll",
    "id": "TSC_772",
    "dbfId": 77209,
    "set": "THE_SUNKEN_CITY",
    "type": "SPELL"
  },
  {
    "name": "Worthy Expedition",
    "id": "ULD_136",
    "dbfId": 53596,
    "set": "ULDUM",
    "type": "SPELL"
  },
  {
    "name": "Sinister Deal",
    "id": "ULD_160",
    "dbfId": 53882,
    "set": "ULDUM",
    "type": "SPELL"
  },
  {
    "name": "Golden Scarab",
    "id": "ULD_188",
    "dbfId": 54264,
    "set": "ULDUM",
    "type": "MINION"
  },
  {
    "name": "Frightened Flunky",
    "id": "ULD_195",
    "dbfId": 54274,
    "set": "ULDUM",
    "type": "MINION"
  },
  {
    "name": "Vulpera Scoundrel",
    "id": "ULD_209",
    "dbfId": 53413,
    "set": "ULDUM",
    "type": "MINION"
  },
  {
    "name": "Tortollan Pilgrim",
    "id": "ULD_236",
    "dbfId": 53771,
    "set": "ULDUM",
    "type": "MINION"
  },
  {
    "name": "Sir Finley of the Sands",
    "id": "ULD_500",
    "dbfId": 53379,
    "set": "ULDUM",
    "type": "MINION"
  },
  {
    "name": "Body Wrapper",
    "id": "ULD_727",
    "dbfId": 54783,
    "set": "ULDUM",
    "type": "MINION"
  },
  {
    "name": "Hydrologist",
    "id": "UNG_011",
    "dbfId": 41139,
    "set": "UNGORO",
    "type": "MINION"
  },
  {
    "name": "Shadow Visions",
    "id": "UNG_029",
    "dbfId": 41169,
    "set": "UNGORO",
    "type": "SPELL"
  },
  {
    "name": "Stonehill Defender",
    "id": "UNG_072",
    "dbfId": 41243,
    "set": "UNGORO",
    "type": "MINION"
  },
  {
    "name": "Tortollan Primalist",
    "id": "UNG_088",
    "dbfId": 41264,
    "set": "UNGORO",
    "type": "MINION"
  },
  {
    "name": "Servant of Kalimos",
    "id": "UNG_816",
    "dbfId": 41410,
    "set": "UNGORO",
    "type": "MINION"
  },
  {
    "name": "Chittering Tunneler",
    "id": "UNG_835",
    "dbfId": 41875,
    "set": "UNGORO",
    "type": "MINION"
  },
  {
    "name": "Free From Amber",
    "id": "UNG_854",
    "dbfId": 42009,
    "set": "UNGORO",
    "type": "SPELL"
  },
  {
    "name": "Hallucination",
    "id": "UNG_856",
    "dbfId": 42011,
    "set": "UNGORO",
    "type": "SPELL"
  },
  {
    "name": "Choose Your Path",
    "id": "UNG_922t1",
    "dbfId": 42881,
    "set": "UNGORO",
    "type": "SPELL"
  },
  {
    "name": "Primalfin Lookout",
    "id": "UNG_937",
    "dbfId": 41478,
    "set": "UNGORO",
    "type": "MINION"
  },
  {
    "name": "Primordial Glyph",
    "id": "UNG_941",
    "dbfId": 41496,
    "set": "UNGORO",
    "type": "SPELL"
  },
  {
    "name": "Cleric of An'she",
    "id": "WC_803",
    "dbfId": 63464,
    "set": "THE_BARRENS",
    "type": "MINION"
  },
  {
    "name": "Cleric of Scales",
    "id": "YOD_013",
    "dbfId": 56088,
    "set": "YEAR_OF_THE_DRAGON",
    "type": "MINION"
  },
  {
    "name": "Dark Prophecy",
    "id": "YOD_015",
    "dbfId": 56090,
    "set": "YEAR_OF_THE_DRAGON",
    "type": "SPELL"
  },
  {
    "name": "Waxmancy",
    "id": "YOD_018",
    "dbfId": 56094,
    "set": "YEAR_OF_THE_DRAGON",
    "type": "SPELL"
  },
  {
    "name": "Boom Squad",
    "id": "YOD_023",
    "dbfId": 56101,
    "set": "YEAR_OF_THE_DRAGON",
    "type": "SPELL"
  },
  {
    "name": "Twisted Knowledge",
    "id": "YOD_025",
    "dbfId": 56109,
    "set": "YEAR_OF_THE_DRAGON",
    "type": "SPELL"
  },
  {
    "name": "Illidari Studies",
    "id": "YOP_001",
    "dbfId": 61939,
    "set": "DARKMOON_FAIRE",
    "type": "SPELL"
  },
  {
    "name": "Keywarden Ivory",
    "id": "YOP_018",
    "dbfId": 61956,
    "set": "DARKMOON_FAIRE",
    "type": "MINION"
  },
  {
    "name": "Resizing Pouch",
    "id": "YOP_029",
    "dbfId": 61967,
    "set": "DARKMOON_FAIRE",
    "type": "SPELL"
  }
]